{"time":{"updated":"Jun 23, 2021 15:53:00 UTC","updatedISO":"2021-06-23T15:53:00+00:00","updateduk":"Jun 23, 2021 at 16:53 BST"},"disclaimer":"This data was produced from the CoinDesk Bitcoin Price Index (USD). Non-USD currency data converted using hourly conversion rate from openexchangerates.org","chartName":"Bitcoin","bpi":{"USD":{"code":"USD","symbol":"&#36;","rate":"33,491.5460","description":"United States Dollar","rate_float":33491.546},"GBP":{"code":"GBP","symbol":"&pound;","rate":"23,977.3346","description":"British Pound Sterling","rate_float":23977.3346},"EUR":{"code":"EUR","symbol":"&euro;","rate":"28,033.4287","description":"Euro","rate_float":28033.4287}}}