{"time":{"updated":"Aug 21, 2021 19:27:00 UTC","updatedISO":"2021-08-21T19:27:00+00:00","updateduk":"Aug 21, 2021 at 20:27 BST"},"disclaimer":"This data was produced from the CoinDesk Bitcoin Price Index (USD). Non-USD currency data converted using hourly conversion rate from openexchangerates.org","chartName":"Bitcoin","bpi":{"USD":{"code":"USD","symbol":"&#36;","rate":"49,077.9922","description":"United States Dollar","rate_float":49077.9922},"GBP":{"code":"GBP","symbol":"&pound;","rate":"36,027.1725","description":"British Pound Sterling","rate_float":36027.1725},"EUR":{"code":"EUR","symbol":"&euro;","rate":"41,957.7571","description":"Euro","rate_float":41957.7571}}}