{"time":{"updated":"Sep 22, 2021 17:06:00 UTC","updatedISO":"2021-09-22T17:06:00+00:00","updateduk":"Sep 22, 2021 at 18:06 BST"},"disclaimer":"This data was produced from the CoinDesk Bitcoin Price Index (USD). Non-USD currency data converted using hourly conversion rate from openexchangerates.org","chartName":"Bitcoin","bpi":{"USD":{"code":"USD","symbol":"&#36;","rate":"43,198.9233","description":"United States Dollar","rate_float":43198.9233},"GBP":{"code":"GBP","symbol":"&pound;","rate":"31,640.5762","description":"British Pound Sterling","rate_float":31640.5762},"EUR":{"code":"EUR","symbol":"&euro;","rate":"36,810.9257","description":"Euro","rate_float":36810.9257}}}