{"time":{"updated":"Sep 10, 2021 18:46:00 UTC","updatedISO":"2021-09-10T18:46:00+00:00","updateduk":"Sep 10, 2021 at 19:46 BST"},"disclaimer":"This data was produced from the CoinDesk Bitcoin Price Index (USD). Non-USD currency data converted using hourly conversion rate from openexchangerates.org","chartName":"Bitcoin","bpi":{"USD":{"code":"USD","symbol":"&#36;","rate":"45,744.4411","description":"United States Dollar","rate_float":45744.4411},"GBP":{"code":"GBP","symbol":"&pound;","rate":"33,040.4322","description":"British Pound Sterling","rate_float":33040.4322},"EUR":{"code":"EUR","symbol":"&euro;","rate":"38,716.6311","description":"Euro","rate_float":38716.6311}}}