{"time":{"updated":"Jun 26, 2021 14:46:00 UTC","updatedISO":"2021-06-26T14:46:00+00:00","updateduk":"Jun 26, 2021 at 15:46 BST"},"disclaimer":"This data was produced from the CoinDesk Bitcoin Price Index (USD). Non-USD currency data converted using hourly conversion rate from openexchangerates.org","chartName":"Bitcoin","bpi":{"USD":{"code":"USD","symbol":"&#36;","rate":"30,998.3133","description":"United States Dollar","rate_float":30998.3133},"GBP":{"code":"GBP","symbol":"&pound;","rate":"22,325.0473","description":"British Pound Sterling","rate_float":22325.0473},"EUR":{"code":"EUR","symbol":"&euro;","rate":"25,970.2319","description":"Euro","rate_float":25970.2319}}}