{"time":{"updated":"Jul 14, 2021 18:40:00 UTC","updatedISO":"2021-07-14T18:40:00+00:00","updateduk":"Jul 14, 2021 at 19:40 BST"},"disclaimer":"This data was produced from the CoinDesk Bitcoin Price Index (USD). Non-USD currency data converted using hourly conversion rate from openexchangerates.org","chartName":"Bitcoin","bpi":{"USD":{"code":"USD","symbol":"&#36;","rate":"33,024.8842","description":"United States Dollar","rate_float":33024.8842},"GBP":{"code":"GBP","symbol":"&pound;","rate":"23,839.0457","description":"British Pound Sterling","rate_float":23839.0457},"EUR":{"code":"EUR","symbol":"&euro;","rate":"27,925.8420","description":"Euro","rate_float":27925.842}}}