{"time":{"updated":"Jun 16, 2021 16:23:00 UTC","updatedISO":"2021-06-16T16:23:00+00:00","updateduk":"Jun 16, 2021 at 17:23 BST"},"disclaimer":"This data was produced from the CoinDesk Bitcoin Price Index (USD). Non-USD currency data converted using hourly conversion rate from openexchangerates.org","chartName":"Bitcoin","bpi":{"USD":{"code":"USD","symbol":"&#36;","rate":"39,057.7535","description":"United States Dollar","rate_float":39057.7535},"GBP":{"code":"GBP","symbol":"&pound;","rate":"27,683.1202","description":"British Pound Sterling","rate_float":27683.1202},"EUR":{"code":"EUR","symbol":"&euro;","rate":"32,231.4346","description":"Euro","rate_float":32231.4346}}}