{"time":{"updated":"Aug 6, 2021 14:20:00 UTC","updatedISO":"2021-08-06T14:20:00+00:00","updateduk":"Aug 6, 2021 at 15:20 BST"},"disclaimer":"This data was produced from the CoinDesk Bitcoin Price Index (USD). Non-USD currency data converted using hourly conversion rate from openexchangerates.org","chartName":"Bitcoin","bpi":{"USD":{"code":"USD","symbol":"&#36;","rate":"40,816.3006","description":"United States Dollar","rate_float":40816.3006},"GBP":{"code":"GBP","symbol":"&pound;","rate":"29,390.1038","description":"British Pound Sterling","rate_float":29390.1038},"EUR":{"code":"EUR","symbol":"&euro;","rate":"34,666.7943","description":"Euro","rate_float":34666.7943}}}