{"time":{"updated":"Sep 23, 2021 19:15:00 UTC","updatedISO":"2021-09-23T19:15:00+00:00","updateduk":"Sep 23, 2021 at 20:15 BST"},"disclaimer":"This data was produced from the CoinDesk Bitcoin Price Index (USD). Non-USD currency data converted using hourly conversion rate from openexchangerates.org","chartName":"Bitcoin","bpi":{"USD":{"code":"USD","symbol":"&#36;","rate":"44,825.6272","description":"United States Dollar","rate_float":44825.6272},"GBP":{"code":"GBP","symbol":"&pound;","rate":"32,642.7389","description":"British Pound Sterling","rate_float":32642.7389},"EUR":{"code":"EUR","symbol":"&euro;","rate":"38,160.1013","description":"Euro","rate_float":38160.1013}}}