{"time":{"updated":"Jun 26, 2021 18:45:00 UTC","updatedISO":"2021-06-26T18:45:00+00:00","updateduk":"Jun 26, 2021 at 19:45 BST"},"disclaimer":"This data was produced from the CoinDesk Bitcoin Price Index (USD). Non-USD currency data converted using hourly conversion rate from openexchangerates.org","chartName":"Bitcoin","bpi":{"USD":{"code":"USD","symbol":"&#36;","rate":"31,631.2683","description":"United States Dollar","rate_float":31631.2683},"GBP":{"code":"GBP","symbol":"&pound;","rate":"22,780.9027","description":"British Pound Sterling","rate_float":22780.9027},"EUR":{"code":"EUR","symbol":"&euro;","rate":"26,500.5185","description":"Euro","rate_float":26500.5185}}}