{"time":{"updated":"Sep 1, 2021 03:54:00 UTC","updatedISO":"2021-09-01T03:54:00+00:00","updateduk":"Sep 1, 2021 at 04:54 BST"},"disclaimer":"This data was produced from the CoinDesk Bitcoin Price Index (USD). Non-USD currency data converted using hourly conversion rate from openexchangerates.org","chartName":"Bitcoin","bpi":{"USD":{"code":"USD","symbol":"&#36;","rate":"46,906.2637","description":"United States Dollar","rate_float":46906.2637},"GBP":{"code":"GBP","symbol":"&pound;","rate":"34,148.4167","description":"British Pound Sterling","rate_float":34148.4167},"EUR":{"code":"EUR","symbol":"&euro;","rate":"39,740.6283","description":"Euro","rate_float":39740.6283}}}