{"time":{"updated":"Aug 23, 2021 02:29:00 UTC","updatedISO":"2021-08-23T02:29:00+00:00","updateduk":"Aug 23, 2021 at 03:29 BST"},"disclaimer":"This data was produced from the CoinDesk Bitcoin Price Index (USD). Non-USD currency data converted using hourly conversion rate from openexchangerates.org","chartName":"Bitcoin","bpi":{"USD":{"code":"USD","symbol":"&#36;","rate":"49,830.4868","description":"United States Dollar","rate_float":49830.4868},"GBP":{"code":"GBP","symbol":"&pound;","rate":"36,508.3062","description":"British Pound Sterling","rate_float":36508.3062},"EUR":{"code":"EUR","symbol":"&euro;","rate":"42,540.8845","description":"Euro","rate_float":42540.8845}}}