{"time":{"updated":"Sep 1, 2021 21:17:00 UTC","updatedISO":"2021-09-01T21:17:00+00:00","updateduk":"Sep 1, 2021 at 22:17 BST"},"disclaimer":"This data was produced from the CoinDesk Bitcoin Price Index (USD). Non-USD currency data converted using hourly conversion rate from openexchangerates.org","chartName":"Bitcoin","bpi":{"USD":{"code":"USD","symbol":"&#36;","rate":"48,427.4050","description":"United States Dollar","rate_float":48427.405},"GBP":{"code":"GBP","symbol":"&pound;","rate":"35,170.5966","description":"British Pound Sterling","rate_float":35170.5966},"EUR":{"code":"EUR","symbol":"&euro;","rate":"40,900.8661","description":"Euro","rate_float":40900.8661}}}