{"time":{"updated":"Jun 29, 2021 15:36:00 UTC","updatedISO":"2021-06-29T15:36:00+00:00","updateduk":"Jun 29, 2021 at 16:36 BST"},"disclaimer":"This data was produced from the CoinDesk Bitcoin Price Index (USD). Non-USD currency data converted using hourly conversion rate from openexchangerates.org","chartName":"Bitcoin","bpi":{"USD":{"code":"USD","symbol":"&#36;","rate":"36,219.9567","description":"United States Dollar","rate_float":36219.9567},"GBP":{"code":"GBP","symbol":"&pound;","rate":"26,182.0665","description":"British Pound Sterling","rate_float":26182.0665},"EUR":{"code":"EUR","symbol":"&euro;","rate":"30,425.3431","description":"Euro","rate_float":30425.3431}}}