{"time":{"updated":"Jul 4, 2021 19:50:00 UTC","updatedISO":"2021-07-04T19:50:00+00:00","updateduk":"Jul 4, 2021 at 20:50 BST"},"disclaimer":"This data was produced from the CoinDesk Bitcoin Price Index (USD). Non-USD currency data converted using hourly conversion rate from openexchangerates.org","chartName":"Bitcoin","bpi":{"USD":{"code":"USD","symbol":"&#36;","rate":"35,513.1800","description":"United States Dollar","rate_float":35513.18},"GBP":{"code":"GBP","symbol":"&pound;","rate":"25,692.2942","description":"British Pound Sterling","rate_float":25692.2942},"EUR":{"code":"EUR","symbol":"&euro;","rate":"29,931.0408","description":"Euro","rate_float":29931.0408}}}