{"time":{"updated":"Jul 9, 2021 19:49:00 UTC","updatedISO":"2021-07-09T19:49:00+00:00","updateduk":"Jul 9, 2021 at 20:49 BST"},"disclaimer":"This data was produced from the CoinDesk Bitcoin Price Index (USD). Non-USD currency data converted using hourly conversion rate from openexchangerates.org","chartName":"Bitcoin","bpi":{"USD":{"code":"USD","symbol":"&#36;","rate":"33,365.3733","description":"United States Dollar","rate_float":33365.3733},"GBP":{"code":"GBP","symbol":"&pound;","rate":"24,021.6007","description":"British Pound Sterling","rate_float":24021.6007},"EUR":{"code":"EUR","symbol":"&euro;","rate":"28,093.7111","description":"Euro","rate_float":28093.7111}}}