{"time":{"updated":"Jul 19, 2021 22:33:00 UTC","updatedISO":"2021-07-19T22:33:00+00:00","updateduk":"Jul 19, 2021 at 23:33 BST"},"disclaimer":"This data was produced from the CoinDesk Bitcoin Price Index (USD). Non-USD currency data converted using hourly conversion rate from openexchangerates.org","chartName":"Bitcoin","bpi":{"USD":{"code":"USD","symbol":"&#36;","rate":"30,853.5450","description":"United States Dollar","rate_float":30853.545},"GBP":{"code":"GBP","symbol":"&pound;","rate":"22,562.3336","description":"British Pound Sterling","rate_float":22562.3336},"EUR":{"code":"EUR","symbol":"&euro;","rate":"26,151.8350","description":"Euro","rate_float":26151.835}}}