{"time":{"updated":"Aug 31, 2021 23:19:00 UTC","updatedISO":"2021-08-31T23:19:00+00:00","updateduk":"Sep 1, 2021 at 00:19 BST"},"disclaimer":"This data was produced from the CoinDesk Bitcoin Price Index (USD). Non-USD currency data converted using hourly conversion rate from openexchangerates.org","chartName":"Bitcoin","bpi":{"USD":{"code":"USD","symbol":"&#36;","rate":"47,147.0797","description":"United States Dollar","rate_float":47147.0797},"GBP":{"code":"GBP","symbol":"&pound;","rate":"34,276.9642","description":"British Pound Sterling","rate_float":34276.9642},"EUR":{"code":"EUR","symbol":"&euro;","rate":"39,920.5639","description":"Euro","rate_float":39920.5639}}}