{"time":{"updated":"Jul 7, 2021 05:58:00 UTC","updatedISO":"2021-07-07T05:58:00+00:00","updateduk":"Jul 7, 2021 at 06:58 BST"},"disclaimer":"This data was produced from the CoinDesk Bitcoin Price Index (USD). Non-USD currency data converted using hourly conversion rate from openexchangerates.org","chartName":"Bitcoin","bpi":{"USD":{"code":"USD","symbol":"&#36;","rate":"34,861.1833","description":"United States Dollar","rate_float":34861.1833},"GBP":{"code":"GBP","symbol":"&pound;","rate":"25,258.0080","description":"British Pound Sterling","rate_float":25258.008},"EUR":{"code":"EUR","symbol":"&euro;","rate":"29,484.0550","description":"Euro","rate_float":29484.055}}}