{"time":{"updated":"Sep 27, 2021 11:16:00 UTC","updatedISO":"2021-09-27T11:16:00+00:00","updateduk":"Sep 27, 2021 at 12:16 BST"},"disclaimer":"This data was produced from the CoinDesk Bitcoin Price Index (USD). Non-USD currency data converted using hourly conversion rate from openexchangerates.org","chartName":"Bitcoin","bpi":{"USD":{"code":"USD","symbol":"&#36;","rate":"43,691.3087","description":"United States Dollar","rate_float":43691.3087},"GBP":{"code":"GBP","symbol":"&pound;","rate":"31,894.5680","description":"British Pound Sterling","rate_float":31894.568},"EUR":{"code":"EUR","symbol":"&euro;","rate":"37,318.5381","description":"Euro","rate_float":37318.5381}}}