{"time":{"updated":"Jun 21, 2021 06:31:00 UTC","updatedISO":"2021-06-21T06:31:00+00:00","updateduk":"Jun 21, 2021 at 07:31 BST"},"disclaimer":"This data was produced from the CoinDesk Bitcoin Price Index (USD). Non-USD currency data converted using hourly conversion rate from openexchangerates.org","chartName":"Bitcoin","bpi":{"USD":{"code":"USD","symbol":"&#36;","rate":"32,866.4104","description":"United States Dollar","rate_float":32866.4104},"GBP":{"code":"GBP","symbol":"&pound;","rate":"23,799.9481","description":"British Pound Sterling","rate_float":23799.9481},"EUR":{"code":"EUR","symbol":"&euro;","rate":"27,691.9227","description":"Euro","rate_float":27691.9227}}}